MANIFEST.in
README
patchqueue.py
setup.py
sphinx_patchqueue.egg-info/PKG-INFO
sphinx_patchqueue.egg-info/SOURCES.txt
sphinx_patchqueue.egg-info/dependency_links.txt
sphinx_patchqueue.egg-info/requires.txt
sphinx_patchqueue.egg-info/top_level.txt