Metadata-Version: 1.0
Name: sphinx-patchqueue
Version: 0.2
Summary: Sphinx extension for embedding sequences of file alterations
Home-page: https://bitbucket.org/masklinn/sphinx-patchqueue
Author: Xavier Morel
Author-email: xavier.morel@masklinn.net
License: BSD
Platform: UNKNOWN
